pi_awning_webthing/__init__.py
pi_awning_webthing/app.py
pi_awning_webthing/awning.py
pi_awning_webthing/awning_webthing.py
pi_awning_webthing/motor_tb6612Fng.py
pi_awning_webthing/switch.py
pi_awning_webthing-3.19.dist-info/LICENSE
pi_awning_webthing-3.19.dist-info/METADATA
pi_awning_webthing-3.19.dist-info/WHEEL
pi_awning_webthing-3.19.dist-info/entry_points.txt
pi_awning_webthing-3.19.dist-info/top_level.txt
pi_awning_webthing-3.19.dist-info/RECORD
