Metadata-Version: 2.1
Name: pi-awning-webthing
Version: 3.19
Summary: A web connected terrace awning controller on Raspberry Pi
Home-page: https://github.com/grro/pi_awning_webthing
Author: Gregor Roth
Author-email: gregor.roth@web.de
License: MIT
Keywords: webthings,awning,control,pation,terrace
Platform: UNKNOWN
Classifier: Programming Language :: Python :: 3
Classifier: License :: OSI Approved :: Apache Software License
Classifier: Operating System :: OS Independent
Classifier: Development Status :: 3 - Alpha
Requires-Dist: webthing ==0.15.0
Requires-Dist: RPi.GPIO
